GosuScreenAPI/__init__.py
GosuScreenAPI/api.py
PyGosuScreenAPI-0.0.2.dist-info/METADATA
PyGosuScreenAPI-0.0.2.dist-info/WHEEL
PyGosuScreenAPI-0.0.2.dist-info/top_level.txt
PyGosuScreenAPI-0.0.2.dist-info/RECORD
