Metadata-Version: 2.1
Name: PyGosuScreenAPI
Version: 0.0.2
Summary: Библиотека Python для GosuScreen API
Home-page: https://github.com/zcxw-code/GosuScreenAPI
Author: zcxw
Author-email: zcxw.code@hotmail.com
Classifier: Programming Language :: Python :: 3.10
Classifier: License :: OSI Approved :: MIT License
Classifier: Operating System :: OS Independent
Requires-Python: >=3.7
Requires-Dist: requests
